squealy/__init__.py
squealy/core.py
squealy/django.py
squealy/flask.py
squealy/formatters.py
tests/__init__.py
tests/test_django.py
tests/test_flask.py
tests/test_squealy.py
squealy-0.2.3.dist-info/METADATA
squealy-0.2.3.dist-info/WHEEL
squealy-0.2.3.dist-info/top_level.txt
squealy-0.2.3.dist-info/RECORD
