Metadata-Version: 2.1
Name: squealy
Version: 0.2.3
Summary: A small example package
Home-page: https://github.com/hashedin/squealy
Author: Sripathi Krishnan
Author-email: sripathi.krishnan@hashedin.com
License: UNKNOWN
Platform: UNKNOWN
Classifier: Programming Language :: Python :: 3
Classifier: License :: OSI Approved :: MIT License
Classifier: Operating System :: OS Independent
Requires-Python: >=3.6
Requires-Dist: jinjasql (>=0.1.8)
Requires-Dist: PyYAML
